./.gitignore
./PKG-INFO
./README.md
./pyproject.toml
./vision_agents/plugins/wizper/__init__.py
./vision_agents/plugins/wizper/stt.py
vision_agents_plugins_wizper-0.2.10.dist-info/METADATA
vision_agents_plugins_wizper-0.2.10.dist-info/WHEEL
vision_agents_plugins_wizper-0.2.10.dist-info/RECORD
