Metadata-Version: 2.4
Name: vision-agents-plugins-wizper
Version: 0.2.10
Summary: Wizper plugin for Vision Agents
Project-URL: Documentation, https://visionagents.ai/
Project-URL: Website, https://visionagents.ai/
Project-URL: Source, https://github.com/GetStream/Vision-Agents
License-Expression: MIT
Keywords: AI,agents,fal,turn detection,voice agents
Requires-Python: >=3.10
Requires-Dist: fal-client>=0.7.0
Requires-Dist: vision-agents
